anas1/__init__.py
anas1/anas1.py
anas1-1.0.dist-info/METADATA
anas1-1.0.dist-info/WHEEL
anas1-1.0.dist-info/top_level.txt
anas1-1.0.dist-info/RECORD
