Metadata-Version: 2.4
Name: anas1
Version: 1.0
Summary: This is just a test package
Author: anaskhaan
Author-email: m.anaskhan9861@gmail.com
Requires-Python: >3.6
Dynamic: author
Dynamic: author-email
Dynamic: requires-python
Dynamic: summary
